{
  "kind": "singleType",
  "collectionName": "profiles",
  "info": {
    "name": "profile",
    "description": ""
  },
  "options": {
    "increments": true,
    "timestamps": true,
    "draftAndPublish": true
  },
  "pluginOptions": {},
  "attributes": {
    "user": {
      "plugin": "admin",
      "model": "user"
    },
    "avatar": {
      "model": "file",
      "via": "related",
      "allowedTypes": [
        "images",
        "files",
        "videos"
      ],
      "plugin": "upload",
      "required": false,
      "pluginOptions": {}
    }
  }
}
