{
  "key": "plugin_content_manager_configuration_content_types::api::section.section",
  "value": {
    "uid": "api::section.section",
    "settings": {
      "bulkable": false,
      "filterable": true,
      "searchable": true,
      "pageSize": 20,
      "mainField": "title",
      "defaultSortBy": "updatedAt",
      "defaultSortOrder": "ASC"
    },
    "metadatas": {
      "id": {
        "edit": {},
        "list": {
          "label": "id",
          "searchable": true,
          "sortable": true
        }
      },
      "title": {
        "edit": {
          "label": "title",
          "description": "",
          "placeholder": "",
          "visible": true,
          "editable": true
        },
        "list": {
          "label": "title",
          "searchable": true,
          "sortable": true
        }
      },
      "description": {
        "edit": {
          "label": "description",
          "description": "",
          "placeholder": "",
          "visible": true,
          "editable": true
        },
        "list": {
          "label": "description",
          "searchable": true,
          "sortable": true
        }
      },
      "path": {
        "edit": {
          "label": "path",
          "description": "",
          "placeholder": "",
          "visible": true,
          "editable": true
        },
        "list": {
          "label": "path",
          "searchable": true,
          "sortable": true
        }
      },
      "weight": {
        "edit": {
          "label": "weight",
          "description": "",
          "placeholder": "",
          "visible": true,
          "editable": true
        },
        "list": {
          "label": "weight",
          "searchable": true,
          "sortable": true
        }
      },
      "content": {
        "edit": {
          "label": "content",
          "description": "",
          "placeholder": "",
          "visible": true,
          "editable": true
        },
        "list": {
          "label": "content",
          "searchable": false,
          "sortable": false
        }
      },
      "createdAt": {
        "edit": {
          "label": "createdAt",
          "description": "",
          "placeholder": "",
          "visible": false,
          "editable": true
        },
        "list": {
          "label": "createdAt",
          "searchable": true,
          "sortable": true
        }
      },
      "updatedAt": {
        "edit": {
          "label": "updatedAt",
          "description": "",
          "placeholder": "",
          "visible": false,
          "editable": true
        },
        "list": {
          "label": "updatedAt",
          "searchable": true,
          "sortable": true
        }
      }
    },
    "layouts": {
      "edit": [
        [
          {
            "name": "title",
            "size": 6
          },
          {
            "name": "description",
            "size": 6
          }
        ],
        [
          {
            "name": "path",
            "size": 6
          },
          {
            "name": "weight",
            "size": 4
          }
        ],
        [
          {
            "name": "content",
            "size": 12
          }
        ]
      ],
      "list": [
        "id",
        "title",
        "path",
        "weight",
        "updatedAt"
      ]
    }
  },
  "type": "object",
  "environment": null,
  "tag": null
}