{
  "kind": "collectionType",
  "collectionName": "sections",
  "info": {
    "singularName": "section",
    "pluralName": "sections",
    "displayName": "Section",
    "description": ""
  },
  "options": {
    "draftAndPublish": true,
    "populateCreatorFields": true
  },
  "pluginOptions": {
    "i18n": {
      "localized": true
    }
  },
  "attributes": {
    "title": {
      "type": "string",
      "required": true,
      "pluginOptions": {
        "i18n": {
          "localized": true
        }
      }
    },
    "description": {
      "pluginOptions": {
        "i18n": {
          "localized": true
        }
      },
      "type": "text"
    },
    "path": {
      "pluginOptions": {
        "i18n": {
          "localized": true
        }
      },
      "type": "string",
      "default": "document/dev",
      "required": true,
      "unique": true
    },
    "weight": {
      "pluginOptions": {
        "i18n": {
          "localized": false
        }
      },
      "type": "integer",
      "default": 99
    },
    "content": {
      "pluginOptions": {
        "i18n": {
          "localized": true
        }
      },
      "type": "richtext"
    }
  }
}
